Metadata-Version: 2.1
Name: c14-jpic
Version: 0.0.2
Summary: C14 Python Wrapper
Home-page: https://github.com/Spredzy/python-c14
Author: Yanis Guenane
Author-email: yanis@guenane.org
License: Apache 2.0
Platform: UNKNOWN
Classifier: Environment :: Console
Classifier: Intended Audience :: Developers
Classifier: Intended Audience :: Information Technology
Classifier: License :: OSI Approved :: Apache Software License
Classifier: Operating System :: POSIX :: Linux
Classifier: Programming Language :: Python :: 2.7
